lecroyutils/__init__.py
lecroyutils/control.py
lecroyutils/data.py
lecroyutils-4.0.2.dist-info/LICENSE
lecroyutils-4.0.2.dist-info/METADATA
lecroyutils-4.0.2.dist-info/WHEEL
lecroyutils-4.0.2.dist-info/top_level.txt
lecroyutils-4.0.2.dist-info/RECORD
