Metadata-Version: 2.1
Name: lecroyutils
Version: 4.0.2
Summary: Library to communicate and parse .trc files with/from LeCroy oscilloscopes.
Home-page: https://github.com/sibartel/lecroyutils
Author: Silas Bartel
Author-email: silas.a.bartel@gmail.com
Project-URL: Bug Tracker, https://github.com/sibartel/lecroyutils/issues
Keywords: Parse,LeCroy,Scope,Oscilloscope,TRC
Classifier: Programming Language :: Python :: 3
Classifier: License :: OSI Approved :: MIT License
Classifier: Operating System :: OS Independent
Classifier: Intended Audience :: Developers
Classifier: Intended Audience :: Science/Research
Classifier: Topic :: Scientific/Engineering :: Interface Engine/Protocol Translator
Requires-Python: >=3.6
License-File: LICENSE
Requires-Dist: numpy
Requires-Dist: python-vxi11
